Workbook

Sheet 00_表紙
A1: 00_表紙
A2: 東都精密工業株式会社｜完成三表モデル｜単位：百万円
A3: 会社名 | B3: 東都精密工業株式会社
A4: モデル目的 | B4: 事業計画、資金繰り、財務三表の検証
A5: 基準日 | B5: 2025/03/31
A6: 計算整合性 | B6: =IF(COUNTIF('16_チェック'!D8:D14,"不適合")=0,"適合","不適合") -> 適合
A7: 意思決定への利用可否 | B7: 教育用・実案件への利用不可

Sheet 01_管理
A1: 01_管理
A2: 東都精密工業株式会社｜完成三表モデル｜単位：百万円
A4: 項目 | B4: 設定値 | C4: 説明
A5: 選択シナリオ | B5: Base
A6: 単位 | B6: 百万円
A7: 最低現預金 | B7: 500
A8: 計算順序 | B8: 前提→売上高・人員・原価・固定資産→PL→運転資本→CF→借入金→BS

Sheet 02_資料管理
A1: 02_資料管理
A2: 東都精密工業株式会社｜完成三表モデル｜単位：百万円
A4: 資料番号 | B4: 資料名 | C4: 基準日 | D4: 使用シート | E4: 主要セル | F4: 状況 | G4: 参照先セル
A5: S-01 | B5: 月次試算表 | C5: 2025/03/31 | D5: 03_実績財務諸表 | E5: B8:D30 | F5: 確認済 | G5: 12_PL!B8:B18 / 13_BS!B8:B19
A6: S-02 | B6: 固定資産台帳 | C6: 2025/03/31 | D6: 10_固定資産 | E6: B8:G11 | F6: 差異60を調整済 | G6: 10_固定資産!B8:B11
A7: S-03 | B7: 借入金明細 | C7: 2025/03/31 | D7: 11_借入金 | E7: B8:G11 | F7: 差異50を調整済 | G7: 11_借入金!B8:B11
A8: S-04 | B8: 勘定科目対応表 | C8: 2025/03/31 | D8: 03_実績財務諸表 | E8: 全主要科目 | F8: 確認済 | G8: 03_実績財務諸表!B8:D19

Sheet 03_実績財務諸表
A1: 03_実績財務諸表
A2: 東都精密工業株式会社｜完成三表モデル｜単位：百万円
A4: PL | B4: 2025年3月期 | C4: BS | D4: 2025年3月期
A8: 売上高 | B8: 10000 | C8: 現預金 | D8: 600
A9: 売上原価 | B9: -7000 | C9: 売掛金 | D9: 1500
A10: 売上総利益 | B10: 3000 | C10: 棚卸資産 | D10: 1200
A11: 販売費及び一般管理費 | B11: -1500 | C11: 固定資産 | D11: 2940
A12: EBITDA | B12: 1500 | C12: その他資産 | D12: 760
A13: 減価償却費 | B13: -300 | C13: 資産合計 | D13: 7000
A14: 営業利益 | B14: 1200 | C14: 買掛金 | D14: 900
A15: 支払利息 | B15: -30 | C15: 有利子負債 | D15: 2000
A16: 税引前当期純利益 | B16: 1170 | C16: その他負債 | D16: 1100
A17: 法人税等 | B17: -351 | C17: 資本金等 | D17: 1500
A18: 当期純利益 | B18: 819 | C18: 利益剰余金 | D18: 1500
C19: 負債・純資産合計 | D19: 7000

Sheet 04_正常化調整
A1: 04_正常化調整
A2: 東都精密工業株式会社｜完成三表モデル｜単位：百万円
A4: 番号 | B4: 項目 | C4: 金額 | D4: PL影響 | E4: 根拠 | F4: 採否
A5: 1 | B5: 役員退職金 | C5: 80 | D5: 加算 | E5: 退任役員1名の一過性費用 | F5: 採用

Sheet 05_前提条件
A1: 05_前提条件
A2: 東都精密工業株式会社｜完成三表モデル｜単位：百万円
A7: 前提項目 | B7: 単位 | C7: Base | D7: Upside | E7: Downside | F7: 選択値 | G7: 出所・根拠
A8: 販売数量成長率 | B8: % | C8: 0.04 | D8: 0.07 | E8: -0.03 | F8: =INDEX(C8:E8,1,MATCH('01_管理'!$B$5,$C$7:$E$7,0)) -> 0.04 | G8: 受注計画・営業ヒアリング
A9: 平均販売単価上昇率 | B9: % | C9: 0.01 | D9: 0.02 | E9: 0 | F9: =INDEX(C9:E9,1,MATCH('01_管理'!$B$5,$C$7:$E$7,0)) -> 0.01 | G9: 価格改定方針
A10: 材料費率 | B10: % | C10: 0.42 | D10: 0.4 | E10: 0.46 | F10: =INDEX(C10:E10,1,MATCH('01_管理'!$B$5,$C$7:$E$7,0)) -> 0.42 | G10: 購買計画
A11: 売掛金回転日数 | B11: 日 | C11: 55 | D11: 52 | E11: 62 | F11: =INDEX(C11:E11,1,MATCH('01_管理'!$B$5,$C$7:$E$7,0)) -> 55 | G11: 得意先別回収条件
A12: 棚卸資産回転日数 | B12: 日 | C12: 63 | D12: 58 | E12: 75 | F12: =INDEX(C12:E12,1,MATCH('01_管理'!$B$5,$C$7:$E$7,0)) -> 63 | G12: 在庫方針
A13: 買掛金回転日数 | B13: 日 | C13: 47 | D13: 50 | E13: 42 | F13: =INDEX(C13:E13,1,MATCH('01_管理'!$B$5,$C$7:$E$7,0)) -> 47 | G13: 仕入先別支払条件
A14: 人員増加率 | B14: % | C14: 0.02 | D14: 0.03 | E14: 0 | F14: =INDEX(C14:E14,1,MATCH('01_管理'!$B$5,$C$7:$E$7,0)) -> 0.02 | G14: 人員計画
A15: 一人当たり人件費上昇率 | B15: % | C15: 0.02 | D15: 0.02 | E15: 0.015 | F15: =INDEX(C15:E15,1,MATCH('01_管理'!$B$5,$C$7:$E$7,0)) -> 0.02 | G15: 給与改定方針
A16: その他製造費率 | B16: % | C16: 0.14 | D16: 0.13 | E16: 0.15 | F16: =INDEX(C16:E16,1,MATCH('01_管理'!$B$5,$C$7:$E$7,0)) -> 0.14 | G16: 製造費実績
A17: 販売費及び一般管理費率 | B17: % | C17: 0.15 | D17: 0.145 | E17: 0.16 | F17: =INDEX(C17:E17,1,MATCH('01_管理'!$B$5,$C$7:$E$7,0)) -> 0.15 | G17: 部門別予算
A18: 実効税率 | B18: % | C18: 0.3 | D18: 0.3 | E18: 0.3 | F18: =INDEX(C18:E18,1,MATCH('01_管理'!$B$5,$C$7:$E$7,0)) -> 0.3 | G18: 簡略化した教育用前提
A19: 借入金利 | B19: % | C19: 0.012 | D19: 0.012 | E19: 0.015 | F19: =INDEX(C19:E19,1,MATCH('01_管理'!$B$5,$C$7:$E$7,0)) -> 0.012 | G19: 借入金明細
... A21: 約定返済 | B21: 百万円 | C21: 350 | D21: 350 | E21: 350 | F21: =INDEX(C21:E21,1,MATCH('01_管理'!$B$5,$C$7:$E$7,0)) -> 350 | G21: 借入金明細（初年度。以降は年度別計画）

Sheet 06_売上高
A1: 06_売上高
A2: 東都精密工業株式会社｜完成三表モデル｜単位：百万円
A4: 項目 | B4: 2025年3月期 | C4: 2026年3月期 | D4: 2027年3月期 | E4: 2028年3月期 | F4: 2029年3月期 | G4: 2030年3月期
A8: 販売数量 | B8: 1000 | C8: =B8*(1+'05_前提条件'!F8) -> 1040 | D8: =C8*(1+'05_前提条件'!F8) -> 1081.6 | E8: =D8*(1+'05_前提条件'!F8) -> 1124.864 | F8: =E8*(1+'05_前提条件'!F8) -> 1169.8586 | G8: =F8*(1+'05_前提条件'!F8) -> 1216.6529
A9: 平均販売単価 | B9: 10 | C9: =B9*(1+'05_前提条件'!F9) -> 10.1 | D9: =C9*(1+'05_前提条件'!F9) -> 10.201 | E9: =D9*(1+'05_前提条件'!F9) -> 10.30301 | F9: =E9*(1+'05_前提条件'!F9) -> 10.40604 | G9: =F9*(1+'05_前提条件'!F9) -> 10.510101
A12: 売上高 | B12: 10000 | C12: =C8*C9 -> 10504 | D12: =D8*D9 -> 11033.402 | E12: =E8*E9 -> 11589.485 | F12: =F8*F9 -> 12173.595 | G12: =G8*G9 -> 12787.144

Sheet 07_原価
A1: 07_原価
A2: 東都精密工業株式会社｜完成三表モデル｜単位：百万円
A4: 項目 | B4: 2025年3月期 | C4: 2026年3月期 | D4: 2027年3月期 | E4: 2028年3月期 | F4: 2029年3月期 | G4: 2030年3月期
A8: 材料費 | B8: 4200 | C8: ='06_売上高'!C12*'05_前提条件'!F10 -> 4411.68 | D8: ='06_売上高'!D12*'05_前提条件'!F10 -> 4634.0287 | E8: ='06_売上高'!E12*'05_前提条件'!F10 -> 4867.5837 | F8: ='06_売上高'!F12*'05_前提条件'!F10 -> 5112.9099 | G8: ='06_売上高'!G12*'05_前提条件'!F10 -> 5370.6006
A9: 労務費 | B9: 1400 | C9: ='08_人員'!C10 -> 1456.56 | D9: ='08_人員'!D10 -> 1515.405 | E9: ='08_人員'!E10 -> 1576.6274 | F9: ='08_人員'!F10 -> 1640.3231 | G9: ='08_人員'!G10 -> 1706.5922
A10: その他製造費 | B10: 1400 | C10: ='06_売上高'!C12*'05_前提条件'!F16 -> 1470.56 | D10: ='06_売上高'!D12*'05_前提条件'!F16 -> 1544.6762 | E10: ='06_売上高'!E12*'05_前提条件'!F16 -> 1622.5279 | F10: ='06_売上高'!F12*'05_前提条件'!F16 -> 1704.3033 | G10: ='06_売上高'!G12*'05_前提条件'!F16 -> 1790.2002
A12: 売上原価 | B12: 7000 | C12: =SUM(C8:C10) -> 7338.8 | D12: =SUM(D8:D10) -> 7694.1099 | E12: =SUM(E8:E10) -> 8066.739 | F12: =SUM(F8:F10) -> 8457.5364 | G12: =SUM(G8:G10) -> 8867.393

Sheet 08_人員
A1: 08_人員
A2: 東都精密工業株式会社｜完成三表モデル｜単位：百万円
A4: 項目 | B4: 2025年3月期 | C4: 2026年3月期 | D4: 2027年3月期 | E4: 2028年3月期 | F4: 2029年3月期 | G4: 2030年3月期
A8: 平均人員 | B8: 200 | C8: =B8*(1+'05_前提条件'!F14) -> 204 | D8: =C8*(1+'05_前提条件'!F14) -> 208.08 | E8: =D8*(1+'05_前提条件'!F14) -> 212.2416 | F8: =E8*(1+'05_前提条件'!F14) -> 216.48643 | G8: =F8*(1+'05_前提条件'!F14) -> 220.81616
A9: 一人当たり人件費 | B9: 7 | C9: =B9*(1+'05_前提条件'!F15) -> 7.14 | D9: =C9*(1+'05_前提条件'!F15) -> 7.2828 | E9: =D9*(1+'05_前提条件'!F15) -> 7.428456 | F9: =E9*(1+'05_前提条件'!F15) -> 7.5770251 | G9: =F9*(1+'05_前提条件'!F15) -> 7.7285656
A10: 人件費 | B10: 1400 | C10: =C8*C9 -> 1456.56 | D10: =D8*D9 -> 1515.405 | E10: =E8*E9 -> 1576.6274 | F10: =F8*F9 -> 1640.3231 | G10: =G8*G9 -> 1706.5922

Sheet 09_運転資本
A1: 09_運転資本
A2: 東都精密工業株式会社｜完成三表モデル｜単位：百万円
A4: 項目 | B4: 2025年3月期 | C4: 2026年3月期 | D4: 2027年3月期 | E4: 2028年3月期 | F4: 2029年3月期 | G4: 2030年3月期
A8: 売掛金 | B8: 1500 | C8: ='12_PL'!C8/365*'05_前提条件'!F11 -> 1582.7945 | D8: ='12_PL'!D8/365*'05_前提条件'!F11 -> 1662.5674 | E8: ='12_PL'!E8/365*'05_前提条件'!F11 -> 1746.3608 | F8: ='12_PL'!F8/365*'05_前提条件'!F11 -> 1834.3773 | G8: ='12_PL'!G8/365*'05_前提条件'!F11 -> 1926.83
A9: 棚卸資産 | B9: 1200 | C9: =-'12_PL'!C9/365*'05_前提条件'!F12 -> 1266.697 | D9: =-'12_PL'!D9/365*'05_前提条件'!F12 -> 1328.0245 | E9: =-'12_PL'!E9/365*'05_前提条件'!F12 -> 1392.3413 | F9: =-'12_PL'!F9/365*'05_前提条件'!F12 -> 1459.794 | G9: =-'12_PL'!G9/365*'05_前提条件'!F12 -> 1530.5363
A10: 買掛金 | B10: 900 | C10: =-'12_PL'!C9/365*'05_前提条件'!F13 -> 944.99616 | D10: =-'12_PL'!D9/365*'05_前提条件'!F13 -> 990.7484 | E10: =-'12_PL'!E9/365*'05_前提条件'!F13 -> 1038.7308 | F10: =-'12_PL'!F9/365*'05_前提条件'!F13 -> 1089.0526 | G10: =-'12_PL'!G9/365*'05_前提条件'!F13 -> 1141.8287

Sheet 10_固定資産
A1: 10_固定資産
A2: 東都精密工業株式会社｜完成三表モデル｜単位：百万円
A4: 項目 | B4: 2025年3月期 | C4: 2026年3月期 | D4: 2027年3月期 | E4: 2028年3月期 | F4: 2029年3月期 | G4: 2030年3月期
A8: 期首帳簿価額 | B8: 2640 | C8: =B11 -> 2940 | D8: =C11 -> 3296 | E8: =D11 -> 3666.4 | F8: =E11 -> 3949.76 | G8: =F11 -> 4154.784
A9: 設備投資 | B9: 600 | C9: =CHOOSE(COLUMN()-2,650,700,650,600,600) -> 650 | D9: =CHOOSE(COLUMN()-2,650,700,650,600,600) -> 700 | E9: =CHOOSE(COLUMN()-2,650,700,650,600,600) -> 650 | F9: =CHOOSE(COLUMN()-2,650,700,650,600,600) -> 600 | G9: =CHOOSE(COLUMN()-2,650,700,650,600,600) -> 600
A10: 減価償却費 | B10: -300 | C10: =-C8*10% -> -294 | D10: =-D8*10% -> -329.6 | E10: =-E8*10% -> -366.64 | F10: =-F8*10% -> -394.976 | G10: =-G8*10% -> -415.4784
A11: 期末帳簿価額 | B11: 2940 | C11: =SUM(C8:C10) -> 3296 | D11: =SUM(D8:D10) -> 3666.4 | E11: =SUM(E8:E10) -> 3949.76 | F11: =SUM(F8:F10) -> 4154.784 | G11: =SUM(G8:G10) -> 4339.3056

Sheet 11_借入金
A1: 11_借入金
A2: 東都精密工業株式会社｜完成三表モデル｜単位：百万円
A4: 項目 | B4: 2025年3月期 | C4: 2026年3月期 | D4: 2027年3月期 | E4: 2028年3月期 | F4: 2029年3月期 | G4: 2030年3月期
A8: 期首借入金 | B8: 2350 | C8: =B11 -> 2000 | D8: =C11 -> 1650 | E8: =D11 -> 1300 | F8: =E11 -> 1000 | G8: =F11 -> 700
A9: 新規借入 | B9: 0 | C9: =MAX(0,'01_管理'!$B$7-('13_BS'!B8+'14_CF'!C12-'10_固定資産'!C9+C10)) -> 0 | D9: =MAX(0,'01_管理'!$B$7-('13_BS'!C8+'14_CF'!D12-'10_固定資産'!D9+D10)) -> 0 | E9: =MAX(0,'01_管理'!$B$7-('13_BS'!D8+'14_CF'!E12-'10_固定資産'!E9+E10)) -> 0 | F9: =MAX(0,'01_管理'!$B$7-('13_BS'!E8+'14_CF'!F12-'10_固定資産'!F9+F10)) -> 0 | G9: =MAX(0,'01_管理'!$B$7-('13_BS'!F8+'14_CF'!G12-'10_固定資産'!G9+G10)) -> 0
A10: 返済 | B10: -350 | C10: =-MIN(C8,350) -> -350 | D10: =-MIN(D8,350) -> -350 | E10: =-MIN(E8,300) -> -300 | F10: =-MIN(F8,300) -> -300 | G10: =-MIN(G8,200) -> -200
A11: 期末借入金 | B11: 2000 | C11: =SUM(C8:C10) -> 1650 | D11: =SUM(D8:D10) -> 1300 | E11: =SUM(E8:E10) -> 1000 | F11: =SUM(F8:F10) -> 700 | G11: =SUM(G8:G10) -> 500

Sheet 12_PL
A1: 12_PL
A2: 東都精密工業株式会社｜完成三表モデル｜単位：百万円
A4: 項目 | B4: 2025年3月期 | C4: 2026年3月期 | D4: 2027年3月期 | E4: 2028年3月期 | F4: 2029年3月期 | G4: 2030年3月期
A8: 売上高 | B8: 10000 | C8: ='06_売上高'!C12 -> 10504 | D8: ='06_売上高'!D12 -> 11033.402 | E8: ='06_売上高'!E12 -> 11589.485 | F8: ='06_売上高'!F12 -> 12173.595 | G8: ='06_売上高'!G12 -> 12787.144
A9: 売上原価 | B9: -7000 | C9: =-'07_原価'!C12 -> -7338.8 | D9: =-'07_原価'!D12 -> -7694.1099 | E9: =-'07_原価'!E12 -> -8066.739 | F9: =-'07_原価'!F12 -> -8457.5364 | G9: =-'07_原価'!G12 -> -8867.393
A10: 売上総利益 | B10: 3000 | C10: =SUM(C8:C9) -> 3165.2 | D10: =SUM(D8:D9) -> 3339.2917 | E10: =SUM(E8:E9) -> 3522.746 | F10: =SUM(F8:F9) -> 3716.0587 | G10: =SUM(G8:G9) -> 3919.7513
A11: 販売費及び一般管理費 | B11: -1500 | C11: =-C8*'05_前提条件'!F17 -> -1575.6 | D11: =-D8*'05_前提条件'!F17 -> -1655.0102 | E11: =-E8*'05_前提条件'!F17 -> -1738.4228 | F11: =-F8*'05_前提条件'!F17 -> -1826.0393 | G11: =-G8*'05_前提条件'!F17 -> -1918.0716
A12: EBITDA | B12: 1500 | C12: =SUM(C10:C11) -> 1589.6 | D12: =SUM(D10:D11) -> 1684.2814 | E12: =SUM(E10:E11) -> 1784.3233 | F12: =SUM(F10:F11) -> 1890.0194 | G12: =SUM(G10:G11) -> 2001.6797
A13: 減価償却費 | B13: -300 | C13: ='10_固定資産'!C10 -> -294 | D13: ='10_固定資産'!D10 -> -329.6 | E13: ='10_固定資産'!E10 -> -366.64 | F13: ='10_固定資産'!F10 -> -394.976 | G13: ='10_固定資産'!G10 -> -415.4784
A14: 営業利益 | B14: 1200 | C14: =SUM(C12:C13) -> 1295.6 | D14: =SUM(D12:D13) -> 1354.6814 | E14: =SUM(E12:E13) -> 1417.6833 | F14: =SUM(F12:F13) -> 1495.0434 | G14: =SUM(G12:G13) -> 1586.2013
A15: 支払利息 | B15: -30 | C15: =-'11_借入金'!C8*'05_前提条件'!F19 -> -24 | D15: =-'11_借入金'!D8*'05_前提条件'!F19 -> -19.8 | E15: =-'11_借入金'!E8*'05_前提条件'!F19 -> -15.6 | F15: =-'11_借入金'!F8*'05_前提条件'!F19 -> -12 | G15: =-'11_借入金'!G8*'05_前提条件'!F19 -> -8.4
A16: 税引前当期純利益 | B16: 1170 | C16: =SUM(C14:C15) -> 1271.6 | D16: =SUM(D14:D15) -> 1334.8814 | E16: =SUM(E14:E15) -> 1402.0833 | F16: =SUM(F14:F15) -> 1483.0434 | G16: =SUM(G14:G15) -> 1577.8013
A17: 法人税等 | B17: -351 | C17: =-MAX(0,C16*'05_前提条件'!F18) -> -381.48 | D17: =-MAX(0,D16*'05_前提条件'!F18) -> -400.46443 | E17: =-MAX(0,E16*'05_前提条件'!F18) -> -420.62498 | F17: =-MAX(0,F16*'05_前提条件'!F18) -> -444.91303 | G17: =-MAX(0,G16*'05_前提条件'!F18) -> -473.34038
A18: 当期純利益 | B18: 819 | C18: =SUM(C16:C17) -> 890.12 | D18: =SUM(D16:D17) -> 934.41701 | E18: =SUM(E16:E17) -> 981.45829 | F18: =SUM(F16:F17) -> 1038.1304 | G18: =SUM(G16:G17) -> 1104.4609

Sheet 13_BS
A1: 13_BS
A2: 東都精密工業株式会社｜完成三表モデル｜単位：百万円
A4: 項目 | B4: 2025年3月期 | C4: 2026年3月期 | D4: 2027年3月期 | E4: 2028年3月期 | F4: 2029年3月期 | G4: 2030年3月期
A8: 現預金 | B8: 600 | C8: ='14_CF'!C20 -> 679.62466 | D8: ='14_CF'!D20 -> 798.29359 | E8: ='14_CF'!E20 -> 1096.2641 | F8: ='14_CF'!F20 -> 1524.223 | G8: ='14_CF'!G20 -> 2133.7434
A9: 売掛金 | B9: 1500 | C9: ='09_運転資本'!C8 -> 1582.7945 | D9: ='09_運転資本'!D8 -> 1662.5674 | E9: ='09_運転資本'!E8 -> 1746.3608 | F9: ='09_運転資本'!F8 -> 1834.3773 | G9: ='09_運転資本'!G8 -> 1926.83
A10: 棚卸資産 | B10: 1200 | C10: ='09_運転資本'!C9 -> 1266.697 | D10: ='09_運転資本'!D9 -> 1328.0245 | E10: ='09_運転資本'!E9 -> 1392.3413 | F10: ='09_運転資本'!F9 -> 1459.794 | G10: ='09_運転資本'!G9 -> 1530.5363
A11: 固定資産 | B11: 2940 | C11: ='10_固定資産'!C11 -> 3296 | D11: ='10_固定資産'!D11 -> 3666.4 | E11: ='10_固定資産'!E11 -> 3949.76 | F11: ='10_固定資産'!F11 -> 4154.784 | G11: ='10_固定資産'!G11 -> 4339.3056
A12: その他資産 | B12: 760 | C12: =B12 -> 760 | D12: =C12 -> 760 | E12: =D12 -> 760 | F12: =E12 -> 760 | G12: =F12 -> 760
A13: 資産合計 | B13: 7000 | C13: =SUM(C8:C12) -> 7585.1162 | D13: =SUM(D8:D12) -> 8215.2854 | E13: =SUM(E8:E12) -> 8944.7261 | F13: =SUM(F8:F12) -> 9733.1783 | G13: =SUM(G8:G12) -> 10690.415
A14: 買掛金 | B14: 900 | C14: ='09_運転資本'!C10 -> 944.99616 | D14: ='09_運転資本'!D10 -> 990.7484 | E14: ='09_運転資本'!E10 -> 1038.7308 | F14: ='09_運転資本'!F10 -> 1089.0526 | G14: ='09_運転資本'!G10 -> 1141.8287
A15: 有利子負債 | B15: 2000 | C15: ='11_借入金'!C11 -> 1650 | D15: ='11_借入金'!D11 -> 1300 | E15: ='11_借入金'!E11 -> 1000 | F15: ='11_借入金'!F11 -> 700 | G15: ='11_借入金'!G11 -> 500
A16: その他負債 | B16: 1100 | C16: =B16 -> 1100 | D16: =C16 -> 1100 | E16: =D16 -> 1100 | F16: =E16 -> 1100 | G16: =F16 -> 1100
A17: 資本金等 | B17: 1500 | C17: =B17 -> 1500 | D17: =C17 -> 1500 | E17: =D17 -> 1500 | F17: =E17 -> 1500 | G17: =F17 -> 1500
A18: 利益剰余金 | B18: 1500 | C18: =B18+'12_PL'!C18 -> 2390.12 | D18: =C18+'12_PL'!D18 -> 3324.537 | E18: =D18+'12_PL'!E18 -> 4305.9953 | F18: =E18+'12_PL'!F18 -> 5344.1257 | G18: =F18+'12_PL'!G18 -> 6448.5866
A19: 負債・純資産合計 | B19: 7000 | C19: =SUM(C14:C18) -> 7585.1162 | D19: =SUM(D14:D18) -> 8215.2854 | E19: =SUM(E14:E18) -> 8944.7261 | F19: =SUM(F14:F18) -> 9733.1783 | G19: =SUM(G14:G18) -> 10690.415

Sheet 14_CF
A1: 14_CF
A2: 東都精密工業株式会社｜完成三表モデル｜単位：百万円
A4: 項目 | B4: 2025年3月期 | C4: 2026年3月期 | D4: 2027年3月期 | E4: 2028年3月期 | F4: 2029年3月期 | G4: 2030年3月期
A8: 当期純利益 | B8: 819 | C8: ='12_PL'!C18 -> 890.12 | D8: ='12_PL'!D18 -> 934.41701 | E8: ='12_PL'!E18 -> 981.45829 | F8: ='12_PL'!F18 -> 1038.1304 | G8: ='12_PL'!G18 -> 1104.4609
A9: 減価償却費 | B9: 300 | C9: =-'10_固定資産'!C10 -> 294 | D9: =-'10_固定資産'!D10 -> 329.6 | E9: =-'10_固定資産'!E10 -> 366.64 | F9: =-'10_固定資産'!F10 -> 394.976 | G9: =-'10_固定資産'!G10 -> 415.4784
A10: 運転資本増減 | B10: -100 | C10: =-(('09_運転資本'!C8-'09_運転資本'!B8)+('09_運転資本'!C9-'09_運転資本'!B9)-('09_運転資本'!C10-'09_運転資本'!B10)) -> -104.49534 | D10: =-(('09_運転資本'!D8-'09_運転資本'!C8)+('09_運転資本'!D9-'09_運転資本'!C9)-('09_運転資本'!D10-'09_運転資本'!C10)) -> -95.348073 | E10: =-(('09_運転資本'!E8-'09_運転資本'!D8)+('09_運転資本'!E9-'09_運転資本'!D9)-('09_運転資本'!E10-'09_運転資本'!D10)) -> -100.12782 | F10: =-(('09_運転資本'!F8-'09_運転資本'!E8)+('09_運転資本'!F9-'09_運転資本'!E9)-('09_運転資本'!F10-'09_運転資本'!E10)) -> -105.14743 | G10: =-(('09_運転資本'!G8-'09_運転資本'!F8)+('09_運転資本'!G9-'09_運転資本'!F9)-('09_運転資本'!G10-'09_運転資本'!F10)) -> -110.41893
A12: 営業CF | B12: 1019 | C12: =SUM(C8:C10) -> 1079.6247 | D12: =SUM(D8:D10) -> 1168.6689 | E12: =SUM(E8:E10) -> 1247.9705 | F12: =SUM(F8:F10) -> 1327.959 | G12: =SUM(G8:G10) -> 1409.5203
A14: 設備投資 | B14: -600 | C14: =-'10_固定資産'!C9 -> -650 | D14: =-'10_固定資産'!D9 -> -700 | E14: =-'10_固定資産'!E9 -> -650 | F14: =-'10_固定資産'!F9 -> -600 | G14: =-'10_固定資産'!G9 -> -600
A16: 借入金増減 | B16: -350 | C16: ='11_借入金'!C9+'11_借入金'!C10 -> -350 | D16: ='11_借入金'!D9+'11_借入金'!D10 -> -350 | E16: ='11_借入金'!E9+'11_借入金'!E10 -> -300 | F16: ='11_借入金'!F9+'11_借入金'!F10 -> -300 | G16: ='11_借入金'!G9+'11_借入金'!G10 -> -200
A19: 現預金増減 | B19: 69 | C19: =SUM(C12,C14,C16) -> 79.624658 | D19: =SUM(D12,D14,D16) -> 118.66893 | E19: =SUM(E12,E14,E16) -> 297.97047 | F19: =SUM(F12,F14,F16) -> 427.95898 | G19: =SUM(G12,G14,G16) -> 609.52034
A20: 期末現預金 | B20: 600 | C20: =B20+C19 -> 679.62466 | D20: =C20+D19 -> 798.29359 | E20: =D20+E19 -> 1096.2641 | F20: =E20+F19 -> 1524.223 | G20: =F20+G19 -> 2133.7434

Sheet 15_出力
A1: 15_出力
A2: 東都精密工業株式会社｜完成三表モデル｜単位：百万円
A4: 項目 | B4: 2025年3月期 | C4: 2026年3月期 | D4: 2027年3月期 | E4: 2028年3月期 | F4: 2029年3月期 | G4: 2030年3月期
A8: 売上高 | B8: ='12_PL'!B8 -> 10000 | C8: ='12_PL'!C8 -> 10504 | D8: ='12_PL'!D8 -> 11033.402 | E8: ='12_PL'!E8 -> 11589.485 | F8: ='12_PL'!F8 -> 12173.595 | G8: ='12_PL'!G8 -> 12787.144
A9: 営業利益 | B9: ='12_PL'!B14 -> 1200 | C9: ='12_PL'!C14 -> 1295.6 | D9: ='12_PL'!D14 -> 1354.6814 | E9: ='12_PL'!E14 -> 1417.6833 | F9: ='12_PL'!F14 -> 1495.0434 | G9: ='12_PL'!G14 -> 1586.2013
A10: 期末現預金 | B10: ='13_BS'!B8 -> 600 | C10: ='13_BS'!C8 -> 679.62466 | D10: ='13_BS'!D8 -> 798.29359 | E10: ='13_BS'!E8 -> 1096.2641 | F10: ='13_BS'!F8 -> 1524.223 | G10: ='13_BS'!G8 -> 2133.7434
A11: 有利子負債 | B11: ='13_BS'!B15 -> 2000 | C11: ='13_BS'!C15 -> 1650 | D11: ='13_BS'!D15 -> 1300 | E11: ='13_BS'!E15 -> 1000 | F11: ='13_BS'!F15 -> 700 | G11: ='13_BS'!G15 -> 500
A12: 貸借差額 | B12: ='13_BS'!B13-'13_BS'!B19 -> 0 | C12: ='13_BS'!C13-'13_BS'!C19 -> 9.094947e-13 | D12: ='13_BS'!D13-'13_BS'!D19 -> 0 | E12: ='13_BS'!E13-'13_BS'!E19 -> -1.8189894e-12 | F12: ='13_BS'!F13-'13_BS'!F19 -> 0 | G12: ='13_BS'!G13-'13_BS'!G19 -> 0
A13: EBITDA | B13: ='12_PL'!B12 -> 1500 | C13: ='12_PL'!C12 -> 1589.6 | D13: ='12_PL'!D12 -> 1684.2814 | E13: ='12_PL'!E12 -> 1784.3233 | F13: ='12_PL'!F12 -> 1890.0194 | G13: ='12_PL'!G12 -> 2001.6797
A14: EBITDAマージン | B14: =B13/B8 -> 0.15 | C14: =C13/C8 -> 0.15133283 | D14: =D13/D8 -> 0.15265296 | E14: =E13/E8 -> 0.15396053 | F14: =F13/F8 -> 0.15525565 | G14: =G13/G8 -> 0.15653844
A15: 純有利子負債 | B15: =B11-B10 -> 1400 | C15: =C11-C10 -> 970.37534 | D15: =D11-D10 -> 501.70641 | E15: =E11-E10 -> -96.264064 | F15: =F11-F10 -> -824.22305 | G15: =G11-G10 -> -1633.7434
A16: 最低現預金余裕額 | B16: =B10-'01_管理'!$B$7 -> 100 | C16: =C10-'01_管理'!$B$7 -> 179.62466 | D16: =D10-'01_管理'!$B$7 -> 298.29359 | E16: =E10-'01_管理'!$B$7 -> 596.26406 | F16: =F10-'01_管理'!$B$7 -> 1024.223 | G16: =G10-'01_管理'!$B$7 -> 1633.7434

Sheet 16_チェック
A1: 16_チェック
A2: 東都精密工業株式会社｜完成三表モデル｜単位：百万円
A4: 確認項目 | B4: 基準 | C4: 差額・件数 | D4: 判定 | E4: 対応先
A8: 貸借一致 | B8: 最大差額0.1未満 | C8: =MAX(ABS('13_BS'!C13-'13_BS'!C19),ABS('13_BS'!D13-'13_BS'!D19),ABS('13_BS'!E13-'13_BS'!E19),ABS('13_BS'!F13-'13_BS'!F19),ABS('13_BS'!G13-'13_BS'!G19)) -> 0 | D8: =IF(ABS(C8)<0.1,"適合","不適合") -> 適合 | E8: 13_BS
A9: CF・BS現預金一致 | B9: 最大差額0.1未満 | C9: =MAX(ABS('13_BS'!C8-'14_CF'!C20),ABS('13_BS'!D8-'14_CF'!D20),ABS('13_BS'!E8-'14_CF'!E20),ABS('13_BS'!F8-'14_CF'!F20),ABS('13_BS'!G8-'14_CF'!G20)) -> 0 | D9: =IF(ABS(C9)<0.1,"適合","不適合") -> 適合 | E9: 13_BS / 14_CF
A10: 固定資産ロールフォワード | B10: 最大差額0.1未満 | C10: =MAX(ABS('10_固定資産'!C8+'10_固定資産'!C9+'10_固定資産'!C10-'10_固定資産'!C11),ABS('10_固定資産'!D8+'10_固定資産'!D9+'10_固定資産'!D10-'10_固定資産'!D11),ABS('10_固定資産'!E8+'10_固定資産'!E9+'10_固定資産'!E10-'10_固定資産'!E11),ABS('10_固定資産'!F8+'10_固定資産'!F9+'10_固定資産'!F10-'10_固定資産'!F11),ABS('10_固定資産'!G8+'10_固定資産'!G9+'10_固定資産'!G10-'10_固定資産'!G11)) -> 0 | D10: =IF(ABS(C10)<0.1,"適合","不適合") -> 適合 | E10: 10_固定資産
A11: 借入金ロールフォワード | B11: 最大差額0.1未満 | C11: =MAX(ABS('11_借入金'!C8+'11_借入金'!C9+'11_借入金'!C10-'11_借入金'!C11),ABS('11_借入金'!D8+'11_借入金'!D9+'11_借入金'!D10-'11_借入金'!D11),ABS('11_借入金'!E8+'11_借入金'!E9+'11_借入金'!E10-'11_借入金'!E11),ABS('11_借入金'!F8+'11_借入金'!F9+'11_借入金'!F10-'11_借入金'!F11),ABS('11_借入金'!G8+'11_借入金'!G9+'11_借入金'!G10-'11_借入金'!G11)) -> 0 | D11: =IF(ABS(C11)<0.1,"適合","不適合") -> 適合 | E11: 11_借入金
A12: 予測期間の空欄 | B12: 0件 | C12: =(55-COUNTA('12_PL'!C8:G18))+(60-COUNTA('13_BS'!C8:G19))+(40-COUNTA('14_CF'!C8:G10)-COUNTA('14_CF'!C12:G12)-COUNTA('14_CF'!C14:G14)-COUNTA('14_CF'!C16:G16)-COUNTA('14_CF'!C19:G20)) -> 0 | D12: =IF(ABS(C12)<0.1,"適合","不適合") -> 適合 | E12: 12_PL / 13_BS / 14_CF
A13: Critical未対応 | B13: 0件 | C13: =COUNTIFS('17_指摘事項'!C5:C50,"Critical",'17_指摘事項'!G5:G50,"<>対応済") -> 0 | D13: =IF(ABS(C13)<0.1,"適合","不適合") -> 適合 | E13: 17_指摘事項
A14: 重要前提の根拠 | B14: 空欄なし | C14: =COUNTBLANK('05_前提条件'!G8:G21) -> 0 | D14: =IF(ABS(C14)<0.1,"適合","不適合") -> 適合 | E14: 05_前提条件
A15: 提出可否 | B15: 不適合なし、Majorは留意点として明示 | C15: =COUNTIF(D8:D14,"不適合") -> 0 | D15: =IF(C15>0,"Not ready",IF(COUNTIFS('17_指摘事項'!C5:C50,"Major",'17_指摘事項'!G5:G50,"<>対応済")>0,"Ready with caveats","Ready")) -> Ready with caveats | E15: 17_指摘事項

Sheet 17_指摘事項
A1: 17_指摘事項
A2: 東都精密工業株式会社｜完成三表モデル｜単位：百万円
A4: 番号 | B4: シート・セル | C4: 重要度 | D4: 指摘事項 | E4: 担当者 | F4: 期限 | G4: 対応状況 | H4: 確認者
A5: 1 | B5: 05_前提条件!F12 | C5: Major | D5: Downsideの在庫日数は追加ヒアリング後に更新 | E5: モデル担当 | F5: 2026/07/31 | G5: 留意点として明示 | H5: レビュー担当

Sheet 18_変更履歴
A1: 18_変更履歴
A2: 東都精密工業株式会社｜完成三表モデル｜単位：百万円
A4: 版 | B4: 更新日 | C4: 更新者 | D4: 変更内容 | E4: 影響範囲 | F4: 再確認
A5: v1.1 | B5: 2026/07/25 | C5: Finance Modeling Lab 編集部 | D5: 5年連動、貸借一致、数式チェック、勘定科目対応を修正 | E5: 全シート | F5: 主要チェック適合
