Workbook

Sheet 00_使い方
A1: 運転資本モデル
A2: 東都パーツ株式会社｜単位：百万円
A4: 手順 | B4: 内容 | C4: 確認事項
A5: 1 | B5: 01_前提条件に売上高、売上原価、回転日数を入力 | C5: 青字セルのみ入力
A6: 2 | B6: 売掛金、棚卸資産、買掛金の計算結果を確認 | C6: 緑字は別シート参照
A7: 3 | B7: 05_運転資本で前期差とCF影響を確認 | C7: 運転資本増加はCFマイナス
A8: 4 | B8: 07_チェックがすべて0であることを確認 | C8: 差額が残る場合は提出不可
A11: 利用条件 | B11: 教育目的・実案件への利用不可

Sheet 01_前提条件
A1: 前提条件
A2: 実績と予測を同じ定義で並べます。
A4: 項目 | B4: 2026/3期 実績 | C4: 2027/3期 予測 | D4: 単位 | E4: 出所・判断
A5: 売上高 | B5: 1200 | C5: 1320 | D5: 百万円 | E5: 事業計画
A6: 売上原価 | B6: 720 | C6: 792 | D6: 百万円 | E6: 事業計画
A7: 売掛金回収日数 | B7: 45 | C7: 50 | D7: 日 | E7: 回収条件・滞留分析
A8: 在庫回転日数 | B8: 60 | C8: 65 | D8: 日 | E8: 在庫計画
A9: 買掛金支払日数 | B9: 35 | C9: 40 | D9: 日 | E9: 仕入条件
A10: 年間日数 | B10: 365 | C10: 365 | D10: 日 | E10: 365日固定

Sheet 02_売掛金
A1: 売掛金
A2: 売上高と回収日数から期末残高を計算します。
A4: 項目 | B4: 2026/3期 実績 | C4: 2027/3期 予測 | D4: 単位 | E4: 計算根拠
A5: 売上高 | B5: 1200 | C5: 1320 | D5: 百万円 | E5: 01_前提条件
A6: 回収日数 | B6: 45 | C6: 50 | D6: 日 | E6: 01_前提条件
A8: 売掛金 | B8: ='01_前提条件'!B5/'01_前提条件'!B10*'01_前提条件'!B7 -> 147.94521 | C8: ='01_前提条件'!C5/'01_前提条件'!C10*'01_前提条件'!C7 -> 180.82192 | D8: 百万円 | E8: 売上高÷365日×回収日数

Sheet 03_棚卸資産
A1: 棚卸資産
A2: 売上原価と在庫回転日数から期末残高を計算します。
A4: 項目 | B4: 2026/3期 実績 | C4: 2027/3期 予測 | D4: 単位 | E4: 計算根拠
A5: 売上原価 | B5: 720 | C5: 792 | D5: 百万円 | E5: 01_前提条件
A6: 在庫回転日数 | B6: 60 | C6: 65 | D6: 日 | E6: 01_前提条件
A8: 棚卸資産 | B8: ='01_前提条件'!B6/'01_前提条件'!B10*'01_前提条件'!B8 -> 118.35616 | C8: ='01_前提条件'!C6/'01_前提条件'!C10*'01_前提条件'!C8 -> 141.0411 | D8: 百万円 | E8: 売上原価÷365日×在庫回転日数

Sheet 04_買掛金
A1: 買掛金
A2: 売上原価と支払日数から期末残高を計算します。
A4: 項目 | B4: 2026/3期 実績 | C4: 2027/3期 予測 | D4: 単位 | E4: 計算根拠
A5: 売上原価 | B5: 720 | C5: 792 | D5: 百万円 | E5: 01_前提条件
A6: 支払日数 | B6: 35 | C6: 40 | D6: 日 | E6: 01_前提条件
A8: 買掛金 | B8: ='01_前提条件'!B6/'01_前提条件'!B10*'01_前提条件'!B9 -> 69.041096 | C8: ='01_前提条件'!C6/'01_前提条件'!C10*'01_前提条件'!C9 -> 86.794521 | D8: 百万円 | E8: 売上原価÷365日×支払日数

Sheet 05_運転資本
A1: 正味運転資本
A2: 三勘定を集約し、前期差をキャッシュ・フローへ接続します。
A4: 項目 | B4: 2026/3期 実績 | C4: 2027/3期 予測 | D4: 増減 | E4: CF影響
A5: 売掛金 | B5: ='02_売掛金'!B8 -> 147.94521 | C5: ='02_売掛金'!C8 -> 180.82192 | D5: =C5-B5 -> 32.876712 | E5: =-D5 -> -32.876712
A6: 棚卸資産 | B6: ='03_棚卸資産'!B8 -> 118.35616 | C6: ='03_棚卸資産'!C8 -> 141.0411 | D6: =C6-B6 -> 22.684932 | E6: =-D6 -> -22.684932
A7: 買掛金 | B7: ='04_買掛金'!B8 -> 69.041096 | C7: ='04_買掛金'!C8 -> 86.794521 | D7: =C7-B7 -> 17.753425 | E7: =D7 -> 17.753425
A9: 正味運転資本 | B9: =SUM(B5:B6)-B7 -> 197.26027 | C9: =SUM(C5:C6)-C7 -> 235.06849 | D9: =C9-B9 -> 37.808219 | E9: =-D9 -> -37.808219

Sheet 06_CCC分析
A1: CCC分析
A2: 回収・在庫・支払の三要素を日数で比較します。
A4: 項目 | B4: 2026/3期 実績 | C4: 2027/3期 予測 | D4: 増減 | E4: 読み方
A5: 売掛金回収日数 | B5: ='01_前提条件'!B7 -> 45 | C5: ='01_前提条件'!C7 -> 50 | D5: =C5-B5 -> 5 | E5: 短いほど回収が早い
A6: 在庫回転日数 | B6: ='01_前提条件'!B8 -> 60 | C6: ='01_前提条件'!C8 -> 65 | D6: =C6-B6 -> 5 | E6: 短いほど在庫効率が高い
A7: 買掛金支払日数 | B7: ='01_前提条件'!B9 -> 35 | C7: ='01_前提条件'!C9 -> 40 | D7: =C7-B7 -> 5 | E7: 長いほど支払いまでの期間が長い
A9: CCC | B9: =B5+B6-B7 -> 70 | C9: =C5+C6-C7 -> 75 | D9: =C9-B9 -> 5 | E9: 長期化は運転資金負担の増加を示す

Sheet 07_チェック
A1: モデルチェック
A2: 差額が0であることを確認します。
A4: 確認項目 | B4: 期待値 | C4: 差額 | D4: 判定
A5: 売掛金計算 | B5: 180.82192 | C5: ='02_売掛金'!C8-C5 -> 0 | D5: =IF(ABS(C5)<0.1,"適合","要確認") -> 適合
A6: 棚卸資産計算 | B6: 141.0411 | C6: ='03_棚卸資産'!C8-C6 -> 0 | D6: =IF(ABS(C6)<0.1,"適合","要確認") -> 適合
A7: 買掛金計算 | B7: 86.794521 | C7: ='04_買掛金'!C8-C7 -> 0 | D7: =IF(ABS(C7)<0.1,"適合","要確認") -> 適合
A8: CF影響符号 | B8: -37.808219 | C8: ='05_運転資本'!E9-C8 -> 0 | D8: =IF(ABS(C8)<0.1,"適合","要確認") -> 適合
